[
    {
        "key": "dbln",
        "value": "%7B%2261567616522655%22%3A%22uY5vYEY4%22%2C%2261583065262206%22%3A%22u4Urh1tH%22%7D",
        "domain": "facebook.com",
        "path": "/login/device-based/",
        "hostOnly": false,
        "creation": "2025-11-29T17:50:28.748Z",
        "lastAccessed": "2025-11-29T17:50:28.748Z"
    },
    {
        "key": "sb",
        "value": "iHxjaKmTzrFlcdJVbwdKTM6B",
        "domain": "facebook.com",
        "path": "/",
        "hostOnly": false,
        "creation": "2025-11-29T17:50:28.748Z",
        "lastAccessed": "2025-11-29T17:50:28.748Z"
    },
    {
        "key": "ps_l",
        "value": "1",
        "domain": "facebook.com",
        "path": "/",
        "hostOnly": false,
        "creation": "2025-11-29T17:50:28.748Z",
        "lastAccessed": "2025-11-29T17:50:28.748Z"
    },
    {
        "key": "ps_n",
        "value": "1",
        "domain": "facebook.com",
        "path": "/",
        "hostOnly": false,
        "creation": "2025-11-29T17:50:28.748Z",
        "lastAccessed": "2025-11-29T17:50:28.748Z"
    },
    {
        "key": "pas",
        "value": "61567616522655%3AQD8Fx9DYK5%2C61578671335433%3APmUCkwWa4l%2C61577754909365%3A1gsaPy9ogT%2C61583065262206%3AfkdPOJQyKM",
        "domain": "facebook.com",
        "path": "/",
        "hostOnly": false,
        "creation": "2025-11-29T17:50:28.748Z",
        "lastAccessed": "2025-11-29T17:50:28.748Z"
    },
    {
        "key": "vpd",
        "value": "v1%3B494x266x2.701960802078247",
        "domain": "facebook.com",
        "path": "/",
        "hostOnly": false,
        "creation": "2025-11-29T17:50:28.748Z",
        "lastAccessed": "2025-11-29T17:50:28.748Z"
    },
    {
        "key": "wl_cbv",
        "value": "v2%3Bclient_version%3A2995%3Btimestamp%3A1764240342",
        "domain": "facebook.com",
        "path": "/",
        "hostOnly": false,
        "creation": "2025-11-29T17:50:28.748Z",
        "lastAccessed": "2025-11-29T17:50:28.748Z"
    },
    {
        "key": "dpr",
        "value": "2.9706623554229736",
        "domain": "facebook.com",
        "path": "/",
        "hostOnly": false,
        "creation": "2025-11-29T17:50:28.748Z",
        "lastAccessed": "2025-11-29T17:50:28.748Z"
    },
    {
        "key": "datr",
        "value": "EzIraf1nLYA8gp1S8CQIEnYu",
        "domain": "facebook.com",
        "path": "/",
        "hostOnly": false,
        "creation": "2025-11-29T17:50:28.748Z",
        "lastAccessed": "2025-11-29T17:50:28.748Z"
    },
    {
        "key": "wd",
        "value": "659x1224",
        "domain": "facebook.com",
        "path": "/",
        "hostOnly": false,
        "creation": "2025-11-29T17:50:28.748Z",
        "lastAccessed": "2025-11-29T17:50:28.748Z"
    },
    {
        "key": "c_user",
        "value": "61577754909365",
        "domain": "facebook.com",
        "path": "/",
        "hostOnly": false,
        "creation": "2025-11-29T17:50:28.748Z",
        "lastAccessed": "2025-11-29T17:50:28.749Z"
    },
    {
        "key": "xs",
        "value": "47%3AX-9LvGia6mPZtw%3A2%3A1764438576%3A-1%3A-1",
        "domain": "facebook.com",
        "path": "/",
        "hostOnly": false,
        "creation": "2025-11-29T17:50:28.749Z",
        "lastAccessed": "2025-11-29T17:50:28.749Z"
    },
    {
        "key": "presence",
        "value": "C%7B%22t3%22%3A%5B%5D%2C%22utc3%22%3A1764438602924%2C%22v%22%3A1%7D",
        "domain": "facebook.com",
        "path": "/",
        "hostOnly": false,
        "creation": "2025-11-29T17:50:28.749Z",
        "lastAccessed": "2025-11-29T17:50:28.749Z"
    },
    {
        "key": "fr",
        "value": "1H3ZKMWMNLSNO7Kv3.AWdGflOZIw8gAIKN2N6hMXGL9-TEyH17RIT4vRSk9vJ1uCm7aQU.BpKT42..AAA.0.0.BpKzJQ.AWelIuaQq9faugGz987_wIGDqbU",
        "domain": "facebook.com",
        "path": "/",
        "hostOnly": false,
        "creation": "2025-11-29T17:50:28.749Z",
        "lastAccessed": "2025-11-29T17:50:28.749Z"
    }
]